rsyncer/__init__.py
rsyncer/rsyncer.py
rsyncer-0.1.1.dist-info/LICENSE
rsyncer-0.1.1.dist-info/METADATA
rsyncer-0.1.1.dist-info/WHEEL
rsyncer-0.1.1.dist-info/entry_points.txt
rsyncer-0.1.1.dist-info/top_level.txt
rsyncer-0.1.1.dist-info/RECORD
