Metadata-Version: 2.1
Name: rsyncer
Version: 0.1.1
Summary: Rsync backup tool.
Author-email: Douglas Keller <dg.kllr.jr@gmail.com>
License: MIT License
Project-URL: Homepage, https://github.com/dkllrjr/rsyncer
Project-URL: Repository, https://github.com/dkllrjr/rsyncer.git
License-File: LICENSE
Requires-Dist: click
